{
  "indexes": [
    {
      "collectionGroup": "turnos",
      "queryScope": "COLLECTION",
      "fields": [
        { "fieldPath": "fecha", "order": "ASCENDING" }
      ]
    },
    {
      "collectionGroup": "despachos",
      "queryScope": "COLLECTION",
      "fields": [
        { "fieldPath": "created_at", "order": "ASCENDING" }
      ]
    },
    {
      "collectionGroup": "gastos_ruta",
      "queryScope": "COLLECTION",
      "fields": [
        { "fieldPath": "fecha", "order": "ASCENDING" }
      ]
    },
    {
      "collectionGroup": "movimientos_bodega",
      "queryScope": "COLLECTION",
      "fields": [
        { "fieldPath": "fecha", "order": "ASCENDING" }
      ]
    },
    {
      "collectionGroup": "chequeo_operacional",
      "queryScope": "COLLECTION",
      "fields": [
        { "fieldPath": "operador", "order": "ASCENDING" },
        { "fieldPath": "fecha_chequeo", "order": "ASCENDING" }
      ]
    }
  ],
  "fieldOverrides": []
}
